{
	"eventId": "tCW_egzQTauLR_U3mlpgPQ",
	"eventTime": "2019-09-06T08:56:31.000Z",
	"eventType": "com.okta.saml.tokens.transform",
	"eventTypeVersion": "1.0",
	"contentType": "application/json",
	"cloudEventVersion": "0.1",
	"source": "https://deptva-eval.okta.com/app/departmentofveteranaffairseval_vasuoktatest_1/exk4s6gjem4kmPaKa2p7/sso/saml",
	"data": {
		"context": {
			"request": {
				"id": "XXIfPnLU41YwKfVF@woWSgAAE8Y",
				"method": "GET",
				"url": {
					"value": "https://deptva-eval.okta.com/app/departmentofveteranaffairseval_vasuoktatest_1/exk4s6gjem4kmPaKa2p7/sso/saml?RelayState=T_QQ6MaP0jDO43azVSmE96hcmyiUvbsYjYFOi9sius-0opNddph9ydQI&SAMLRequest=nJLPbts8EMRfReBdJq1YskxEBvzF%2BFCjaWvEbg%2B9BBtqHbPmH5W7cpO3LySnQHrxoVfuzM7gx70l8K7Tq56P4QF%2F9kicvXgXSA%2BDRvQp6AhkSQfwSJqN3q0%2B3etiojQQYWIbg3hn6a57uhQ5muhEtlk3wrZ5UVXGFFMw8%2FamnrdQmlpV5byczapCldMa1PTppkYQ2TdMZGNoRDFRItsQ9bgJxBC4EYWaLnK1yFW1V7UuK63KSTVffBfZGoltAB6dR%2BaOtJQtdnyGHM%2FgJvHEMDHRS%2Bi6YQCJPQaOhzMyJghwOIBNNGgfz0D9oGckfpxKfDnNqHr%2BgX528lv4CEU3l0RRDiBE9n9MBkeyjTiAIxTZ6g%2Byuxio95h2mM7W4NeH%2B0s7LaWLBtwxEutaKTXukmBIZNs3dv%2FZ0NrwfB3000VE%2BsN%2Bv823X3Z7sRw%2FW4%2Fk0tDOA19fMrzYNj%2BMUo2BLb%2BK5ZWeHhlaYLiV76KWb0f2GTxu1tvorHn9h3hOEMhiYJGtnIu%2F7hICYyM49Sjk8hL59ykvfwcAAP%2F%2F&fromLogin=true"
				},
				"ipAddress": "108.185.221.32"
			},
			"protocol": {
				"request": {
					"id": "id-266cc21ac7d387da5c80657544620518a01b38ea",
					"version": "2.0",
					"issuerInstant": "2019-09-06T08:56:05.000Z",
					"destination": "https://deptva-eval.okta.com/app/departmentofveteranaffairseval_vasuoktatest_1/exk4s6gjem4kmPaKa2p7/sso/saml",
					"forceAuthn": false,
					"passive": false,
					"issuer": "http://localhost:8000/saml/metadata",
					"assertionConsumerServiceURL": "http://localhost:8000/saml/acs",
					"protocolBinding": "urn:oasis:names:tc:SAML:2.0:bindings:HTTP-POST",
					"nameIdPolicy": {
						"format": "urn:oasis:names:tc:SAML:2.0:nameid-format:transient",
						"allowCreate": true
					},
					"relayState": "T_QQ6MaP0jDO43azVSmE96hcmyiUvbsYjYFOi9sius-0opNddph9ydQI"
				},
				"type": "SAML2.0",
				"issuer": {
					"id": "0oa4s6gjen3jPPFMX2p7",
					"name": "VASU SAML Test App",
					"uri": "http://www.okta.com/sso-vasu"
				}
			},
			"session": {
				"id": "102xRhrERq4TomXiYo35G_ZlQ",
				"userId": "00u3z5e6as6tEwXWx2p7",
				"login": "b24346a788c04dfea5048d44ad071181",
				"createdAt": "2019-09-06T08:56:30.000Z",
				"expiresAt": "2019-09-06T08:57:30.000Z",
				"status": "ACTIVE",
				"amr": ["PASSWORD"],
				"idp": {
					"id": "0oa1pbnlkmlWpo0q22p7",
					"type": "FEDERATION"
				},
				"mfaActive": false
			},
			"user": {
				"id": "00u3z5e6as6tEwXWx2p7",
				"passwordChanged": "2019-05-16T18:28:18.000Z",
				"profile": {
					"login": "b24346a788c04dfea5048d44ad071181",
					"firstName": "Tamara",
					"lastName": "Ellis",
					"locale": "en",
					"timeZone": "America/Los_Angeles"
				},
				"_links": {
					"groups": {
						"href": "https://deptva-eval.okta.com/00u3z5e6as6tEwXWx2p7/groups"
					},
					"factors": {
						"href": "https://deptva-eval.okta.com/api/v1/users/00u3z5e6as6tEwXWx2p7/factors"
					}
				}
			}
		},
		"assertion": {
			"subject": {
				"nameId": "b24346a788c04dfea5048d44ad071181",
				"nameFormat": "urn:oasis:names:tc:SAML:1.1:nameid-format:unspecified",
				"confirmation": {
					"method": "urn:oasis:names:tc:SAML:2.0:cm:bearer",
					"data": {
						"inResponseTo": "id-266cc21ac7d387da5c80657544620518a01b38ea",
						"recipient": "http://localhost:8000/saml/acs"
					}
				}
			},
			"authentication": {
				"sessionIndex": "id-266cc21ac7d387da5c80657544620518a01b38ea",
				"authnContext": {
					"authnContextClassRef": "urn:oasis:names:tc:SAML:2.0:ac:classes:PasswordProtectedTransport"
				}
			},
			"conditions": {
				"audienceRestriction": ["http://localhost:8000/saml/metadata"]
			},
			"claims": {
				"mhv_icn": {
					"attributes": {
						"NameFormat": "urn:oasis:names:tc:SAML:2.0:attrname-format:unspecified"
					},
					"attributeValues": [{
						"attributes": {
							"xsi:type": "xs:string"
						},
						"value": "1012667145V762142"
					}]
				},
				"first_name": {
					"attributes": {
						"NameFormat": "urn:oasis:names:tc:SAML:2.0:attrname-format:unspecified"
					},
					"attributeValues": [{
						"attributes": {
							"xsi:type": "xs:string"
						},
						"value": "Tamara"
					}]
				},
				"last_name": {
					"attributes": {
						"NameFormat": "urn:oasis:names:tc:SAML:2.0:attrname-format:unspecified"
					},
					"attributeValues": [{
						"attributes": {
							"xsi:type": "xs:string"
						},
						"value": "Ellis"
					}]
				},
				"user_email": {
					"attributes": {
						"NameFormat": "urn:oasis:names:tc:SAML:2.0:attrname-format:unspecified"
					},
					"attributeValues": [{
						"attributes": {
							"xsi:type": "xs:string"
						},
						"value": "va.api.user+idme.001@gmail.com"
					}]
				},
				"idp_uuid": {
					"attributes": {
						"NameFormat": "urn:oasis:names:tc:SAML:2.0:attrname-format:unspecified"
					},
					"attributeValues": [{
						"attributes": {
							"xsi:type": "xs:string"
						},
						"value": "b24346a788c04dfea5048d44ad071181"
					}]
				},
				"gender": {
					"attributes": {
						"NameFormat": "urn:oasis:names:tc:SAML:2.0:attrname-format:unspecified"
					},
					"attributeValues": [{
						"attributes": {
							"xsi:type": "xs:string"
						},
						"value": ""
					}]
				},
				"dob": {
					"attributes": {
						"NameFormat": "urn:oasis:names:tc:SAML:2.0:attrname-format:unspecified"
					},
					"attributeValues": [{
						"attributes": {
							"xsi:type": "xs:string"
						},
						"value": ""
					}]
				},
				"ssn": {
					"attributes": {
						"NameFormat": "urn:oasis:names:tc:SAML:2.0:attrname-format:unspecified"
					},
					"attributeValues": [{
						"attributes": {
							"xsi:type": "xs:string"
						},
						"value": ""
					}]
				},
				"dslogon_edipi": {
					"attributes": {
						"NameFormat": "urn:oasis:names:tc:SAML:2.0:attrname-format:unspecified"
					},
					"attributeValues": [{
						"attributes": {
							"xsi:type": "xs:string"
						},
						"value": ""
					}]
				},
				"level_of_assurance": {
					"attributes": {
						"NameFormat": "urn:oasis:names:tc:SAML:2.0:attrname-format:unspecified"
					},
					"attributeValues": [{
						"attributes": {
							"xsi:type": "xs:string"
						},
						"value": "3"
					}]
				},
				"idp_authn_context": {
					"attributes": {
						"NameFormat": "urn:oasis:names:tc:SAML:2.0:attrname-format:unspecified"
					},
					"attributeValues": [{
						"attributes": {
							"xsi:type": "xs:string"
						},
						"value": "http://idmanagement.gov/ns/assurance/loa/3"
					}]
				}
			},
			"lifetime": {
				"expiration": 300
			}
		}
	},
	"format": "json",
	"controller": "openid_auth/v0/okta",
	"action": "okta_callback",
	"oktum": {
		"eventId": "tCW_egzQTauLR_U3mlpgPQ",
		"eventTime": "2019-09-06T08:56:31.000Z",
		"eventType": "com.okta.saml.tokens.transform",
		"eventTypeVersion": "1.0",
		"contentType": "application/json",
		"cloudEventVersion": "0.1",
		"source": "https://deptva-eval.okta.com/app/departmentofveteranaffairseval_vasuoktatest_1/exk4s6gjem4kmPaKa2p7/sso/saml",
		"data": {
			"context": {
				"request": {
					"id": "XXIfPnLU41YwKfVF@woWSgAAE8Y",
					"method": "GET",
					"url": {
						"value": "https://deptva-eval.okta.com/app/departmentofveteranaffairseval_vasuoktatest_1/exk4s6gjem4kmPaKa2p7/sso/saml?RelayState=T_QQ6MaP0jDO43azVSmE96hcmyiUvbsYjYFOi9sius-0opNddph9ydQI&SAMLRequest=nJLPbts8EMRfReBdJq1YskxEBvzF%2BFCjaWvEbg%2B9BBtqHbPmH5W7cpO3LySnQHrxoVfuzM7gx70l8K7Tq56P4QF%2F9kicvXgXSA%2BDRvQp6AhkSQfwSJqN3q0%2B3etiojQQYWIbg3hn6a57uhQ5muhEtlk3wrZ5UVXGFFMw8%2FamnrdQmlpV5byczapCldMa1PTppkYQ2TdMZGNoRDFRItsQ9bgJxBC4EYWaLnK1yFW1V7UuK63KSTVffBfZGoltAB6dR%2BaOtJQtdnyGHM%2FgJvHEMDHRS%2Bi6YQCJPQaOhzMyJghwOIBNNGgfz0D9oGckfpxKfDnNqHr%2BgX528lv4CEU3l0RRDiBE9n9MBkeyjTiAIxTZ6g%2Byuxio95h2mM7W4NeH%2B0s7LaWLBtwxEutaKTXukmBIZNs3dv%2FZ0NrwfB3000VE%2BsN%2Bv823X3Z7sRw%2FW4%2Fk0tDOA19fMrzYNj%2BMUo2BLb%2BK5ZWeHhlaYLiV76KWb0f2GTxu1tvorHn9h3hOEMhiYJGtnIu%2F7hICYyM49Sjk8hL59ykvfwcAAP%2F%2F&fromLogin=true"
					},
					"ipAddress": "108.185.221.32"
				},
				"protocol": {
					"request": {
						"id": "id-266cc21ac7d387da5c80657544620518a01b38ea",
						"version": "2.0",
						"issuerInstant": "2019-09-06T08:56:05.000Z",
						"destination": "https://deptva-eval.okta.com/app/departmentofveteranaffairseval_vasuoktatest_1/exk4s6gjem4kmPaKa2p7/sso/saml",
						"forceAuthn": false,
						"passive": false,
						"issuer": "http://localhost:8000/saml/metadata",
						"assertionConsumerServiceURL": "http://localhost:8000/saml/acs",
						"protocolBinding": "urn:oasis:names:tc:SAML:2.0:bindings:HTTP-POST",
						"nameIdPolicy": {
							"format": "urn:oasis:names:tc:SAML:2.0:nameid-format:transient",
							"allowCreate": true
						},
						"relayState": "T_QQ6MaP0jDO43azVSmE96hcmyiUvbsYjYFOi9sius-0opNddph9ydQI"
					},
					"type": "SAML2.0",
					"issuer": {
						"id": "0oa4s6gjen3jPPFMX2p7",
						"name": "VASU SAML Test App",
						"uri": "http://www.okta.com/sso-vasu"
					}
				},
				"session": {
					"id": "102xRhrERq4TomXiYo35G_ZlQ",
					"userId": "00u3z5e6as6tEwXWx2p7",
					"login": "b24346a788c04dfea5048d44ad071181",
					"createdAt": "2019-09-06T08:56:30.000Z",
					"expiresAt": "2019-09-06T08:57:30.000Z",
					"status": "ACTIVE",
					"amr": ["PASSWORD"],
					"idp": {
						"id": "0oa1pbnlkmlWpo0q22p7",
						"type": "FEDERATION"
					},
					"mfaActive": false
				},
				"user": {
					"id": "00u3z5e6as6tEwXWx2p7",
					"passwordChanged": "2019-05-16T18:28:18.000Z",
					"profile": {
						"login": "b24346a788c04dfea5048d44ad071181",
						"firstName": "Tamara",
						"lastName": "Ellis",
						"locale": "en",
						"timeZone": "America/Los_Angeles"
					},
					"_links": {
						"groups": {
							"href": "https://deptva-eval.okta.com/00u3z5e6as6tEwXWx2p7/groups"
						},
						"factors": {
							"href": "https://deptva-eval.okta.com/api/v1/users/00u3z5e6as6tEwXWx2p7/factors"
						}
					}
				}
			},
			"assertion": {
				"subject": {
					"nameId": "b24346a788c04dfea5048d44ad071181",
					"nameFormat": "urn:oasis:names:tc:SAML:1.1:nameid-format:unspecified",
					"confirmation": {
						"method": "urn:oasis:names:tc:SAML:2.0:cm:bearer",
						"data": {
							"inResponseTo": "id-266cc21ac7d387da5c80657544620518a01b38ea",
							"recipient": "http://localhost:8000/saml/acs"
						}
					}
				},
				"authentication": {
					"sessionIndex": "id-266cc21ac7d387da5c80657544620518a01b38ea",
					"authnContext": {
						"authnContextClassRef": "urn:oasis:names:tc:SAML:2.0:ac:classes:PasswordProtectedTransport"
					}
				},
				"conditions": {
					"audienceRestriction": ["http://localhost:8000/saml/metadata"]
				},
				"claims": {
					"mhv_icn": {
						"attributes": {
							"NameFormat": "urn:oasis:names:tc:SAML:2.0:attrname-format:unspecified"
						},
						"attributeValues": [{
							"attributes": {
								"xsi:type": "xs:string"
							},
							"value": "1012667145V762142"
						}]
					},
					"first_name": {
						"attributes": {
							"NameFormat": "urn:oasis:names:tc:SAML:2.0:attrname-format:unspecified"
						},
						"attributeValues": [{
							"attributes": {
								"xsi:type": "xs:string"
							},
							"value": "Tamara"
						}]
					},
					"last_name": {
						"attributes": {
							"NameFormat": "urn:oasis:names:tc:SAML:2.0:attrname-format:unspecified"
						},
						"attributeValues": [{
							"attributes": {
								"xsi:type": "xs:string"
							},
							"value": "Ellis"
						}]
					},
					"user_email": {
						"attributes": {
							"NameFormat": "urn:oasis:names:tc:SAML:2.0:attrname-format:unspecified"
						},
						"attributeValues": [{
							"attributes": {
								"xsi:type": "xs:string"
							},
							"value": "va.api.user+idme.001@gmail.com"
						}]
					},
					"idp_uuid": {
						"attributes": {
							"NameFormat": "urn:oasis:names:tc:SAML:2.0:attrname-format:unspecified"
						},
						"attributeValues": [{
							"attributes": {
								"xsi:type": "xs:string"
							},
							"value": "b24346a788c04dfea5048d44ad071181"
						}]
					},
					"gender": {
						"attributes": {
							"NameFormat": "urn:oasis:names:tc:SAML:2.0:attrname-format:unspecified"
						},
						"attributeValues": [{
							"attributes": {
								"xsi:type": "xs:string"
							},
							"value": ""
						}]
					},
					"dob": {
						"attributes": {
							"NameFormat": "urn:oasis:names:tc:SAML:2.0:attrname-format:unspecified"
						},
						"attributeValues": [{
							"attributes": {
								"xsi:type": "xs:string"
							},
							"value": ""
						}]
					},
					"ssn": {
						"attributes": {
							"NameFormat": "urn:oasis:names:tc:SAML:2.0:attrname-format:unspecified"
						},
						"attributeValues": [{
							"attributes": {
								"xsi:type": "xs:string"
							},
							"value": ""
						}]
					},
					"dslogon_edipi": {
						"attributes": {
							"NameFormat": "urn:oasis:names:tc:SAML:2.0:attrname-format:unspecified"
						},
						"attributeValues": [{
							"attributes": {
								"xsi:type": "xs:string"
							},
							"value": ""
						}]
					},
					"level_of_assurance": {
						"attributes": {
							"NameFormat": "urn:oasis:names:tc:SAML:2.0:attrname-format:unspecified"
						},
						"attributeValues": [{
							"attributes": {
								"xsi:type": "xs:string"
							},
							"value": "3"
						}]
					},
					"idp_authn_context": {
						"attributes": {
							"NameFormat": "urn:oasis:names:tc:SAML:2.0:attrname-format:unspecified"
						},
						"attributeValues": [{
							"attributes": {
								"xsi:type": "xs:string"
							},
							"value": "http://idmanagement.gov/ns/assurance/loa/3"
						}]
					}
				},
				"lifetime": {
					"expiration": 300
				}
			}
		}
	}
}