{
  "veteran_information": {
    "full_name": {
      "first": "Adam",
      "middle": "B",
      "last": "Huberws",
      "suffix": "Jr."
    },
    "ssn": "796-10-4437",
    "va_file_number": "796104437",
    "service_number": "123456789",
    "birth_date": "1950-10-04"
  },
  "dependents_application" : {
    "veteran_contact_information": {
      "veteran_address": {
        "country_name": "USA",
        "address_line1": "8200 DOBY LN",
        "city": "PASADENA",
        "state_code": "CA",
        "zip_code": "21122-9876"
      },
      "phone_number": "1112223333",
      "email_address": "vets.gov.user+228@gmail.com"
    },
    "household_income": true,
    "spouse_information": {
      "full_name": {
        "first": "Jenny",
        "middle": "L",
        "last": "McCarthy",
        "suffix": "Sr."
      },
      "ssn": "323454323",
      "birth_date": "1981-04-04",
      "is_veteran": true,
      "va_file_number": "000000000",
      "service_number": "111111111"
    },
    "current_marriage_information": {
      "date": "2014-03-04",
      "location": {
        "state": "CA",
        "city": "Slawson"
      },
      "type": "OTHER",
      "type_other": "Other"
    },
    "does_live_with_spouse": {
      "spouse_does_live_with_veteran": false,
      "spouse_income": false,
      "current_spouse_reason_for_separation": "Other",
      "address": {
        "country_name": "USA",
        "address_line1": "2037 29th St",
        "city": "Rock Island",
        "state_code": "IL",
        "zip_code": "61201"
      }
    }
  }
}
