{
  "$schema": "http://json-schema.org/draft-04/schema#",
  "definitions": {},
  "properties": {
    "data": {
      "properties": {
        "attributes": {       
          "properties": {                    
            "service_history": {
              "description": "Array of service history objects",
              "items": {
                "type": "object"
              },
              "properties": {
                "service_type": {
                  "type": "string"
                },
                "branch_of_service": {
                  "type": "string"
                },
                "begin_date": {
                  "type": "string"
                },
                "end_date": {
                  "type": "string"
                },
                "termination_reason_code": {
                  "type": "string"
                },
                "termination_reason_text": {
                  "type": "string"
                },           
                "period_of_service_type_code": {
                  "type": "string"
                },
                "period_of_service_type_text": {
                  "type": "string"
                }                
              },
              "type": "array"
            },
            "vet_status_eligibility": {
              "description": "Proof of status card eligibility confirmation and message",
              "items": {
                "type": "object"
              },
              "properties": {
                "confirmed": {
                  "type": "boolean"
                },
                "message" : {
                  "type": "array"
                }
              },
              "type": "object"
            }
          },
          "type": "object"
        },
        "id": {
          "type": "string"
        },
        "type": {
          "type": "string"
        }
      },
      "type": "object"
    }
  },
  "type": "object"
}
