{
  "type": "object",
  "definitions": {},
  "$schema": "http://json-schema.org/draft-04/schema#",
  "properties": {
    "id": {
      "type": "integer",
      "examples": [
        12
      ]
    },
    "created_at": {
      "type": "string",
      "examples": [
        "2018-05-10T15:18:43.668Z"
      ]
    },
    "updated_at": {
      "type": "string",
      "examples": [
        "2018-05-10T15:18:43.668Z"
      ]
    },
    "guid": {
      "type": "string",
      "examples": [
        "8f68e6b2-1318-41a1-a80b-cba7d6a7b505"
      ]
    },
    "encrypted_file_data": {
      "type": "string",
      "examples": [
        "jvJNW3DvnVJ2MG1SyO7Fj2se9cO81R8Z7QFVW0l+Zea8\n"
      ]
    },
    "encrypted_file_data_iv": {
      "type": "string",
      "examples": [
        "QhEhcQbOOqr8oFCg\n"
      ]
    }
  }
}
